ethical_rl/__init__.py
ethical_rl/arguments.py
ethical_rl/config.py
ethical_rl/constants.py
ethical_rl/deploy.py
ethical_rl/reporting.py
ethical_rl/reward_predictor.py
ethical_rl/util.py
ethical_rl-0.0.1.dist-info/METADATA
ethical_rl-0.0.1.dist-info/WHEEL
ethical_rl-0.0.1.dist-info/top_level.txt
ethical_rl-0.0.1.dist-info/RECORD
