Metadata-Version: 2.1
Name: ethical-rl
Version: 0.0.1
Summary: Ethical Reinforcement Learning Library
Home-page: https://github.com/arie-glazier/ethical_rl
Author: Arie Glazier
Author-email: adglazier@gmail.com
License: unlicense
Platform: UNKNOWN
Requires-Dist: tensorflow (==2.3.0)
Requires-Dist: gym (==0.17.2)
Requires-Dist: numpy (==1.17.4)
Requires-Dist: gym-minigrid (==1.0.1)
Requires-Dist: matplotlib (==3.3.1)
Requires-Dist: gym[atari]
